Metadata-Version: 2.1
Name: DogTown
Version: 0.0.1
Summary: A Dog Program That is cool
Home-page: UNKNOWN
License: UNKNOWN
Platform: UNKNOWN
